{
  "201904": [
    {
      "id": 1,
      "title": "41111",
      "start_time": "201905082310",
      "end_time": "201905090005"
    },
    {
      "id": 2,
      "title": "42222",
      "start_time": "201905082310",
      "end_time": "201905090005"
    },
    {
      "id": 3,
      "title": "43333",
      "start_time": "201905082310",
      "end_time": "201905090030"
    }
  ],
  "201905": [
    {
      "id": 4,
      "title": "charles",
      "start_time": "201905082310",
      "end_time": "201905090005"
    },
    {
      "id": 5,
      "title": "pddd",
      "start_time": "201905082310",
      "end_time": "201905090005"
    },
    {
      "id": 6,
      "title": "fireddd",
      "start_time": "201905082310",
      "end_time": "201905090030"
    },
    {
      "id": 7,
      "title": "charles",
      "start_time": "201905081300",
      "end_time": "201905081505"
    },
    {
      "id": 11,
      "title": "charles",
      "start_time": "201905081440",
      "end_time": "201905081505"
    }
  ],
  "201906": [
    {
      "id": 8,
      "title": "6111",
      "start_time": "201905082310",
      "end_time": "201905090005"
    },
    {
      "id": 9,
      "title": "6222",
      "start_time": "201905082310",
      "end_time": "201905090005"
    },
    {
      "id": 10,
      "title": "6333",
      "start_time": "201905082310",
      "end_time": "201905090030"
    }
  ]
}